<?xml version = '1.0' encoding = 'UTF-8'?>
<Relation class="oracle.dbtools.crest.model.design.logical.Relation" name="tiene" directorySegmentName="seg_0" id="E9FEC55B-ED3A-4C46-E337-9387B7D566B4">
<createdBy>Javi</createdBy>
<createdTime>2016-06-08 22:37:58 UTC</createdTime>
<ownerDesignName>Playas_BD</ownerDesignName>
<engineerTo>
<item key="2EAF5775-AB44-DC58-9DA7-651E8A9A6C89" value="true"/>
</engineerTo>
<sourcePk>FFA6D721-1FC0-40A8-2686-B4E1017DA464</sourcePk>
<identifying>true</identifying>
<optionalSource>true</optionalSource>
<optionalTarget>false</optionalTarget>
<sourceCardinality>1</sourceCardinality>
<sourceEntity>8A98E526-0784-C4DD-098E-AB60CECCDDF7</sourceEntity>
<targetCardinalityString>*</targetCardinalityString>
<targetEntity>5EEB461D-88B8-044E-E354-2A49A03E9029</targetEntity>
<transferable>true</transferable>
<deleteRule>NO ACTION</deleteRule>
</Relation>